Workbook

Sheet Tender
A1: HANNAH PLUMBING & HEATING LTD - TENDER RETURN
A2: Life Church - Ground Floor Fit Out, 6-8 High Street, Paisley PA1 2YA | Main contractor: Woodvale Projects Ltd
A3: Priced to BOQ Rev3 (Clarification No.2, 30/09/26). Plumbing & drainage package. All prices exclude VAT (domestic reverse charge applies).
A5: Pricing inputs (yellow cells are editable):
A6: Labour rate per hour (£) | D6: 50
A7: Materials mark-up (%) | D7: 0.15
A8: Extra O&P on labour (%) - 0% as hourly rate is the billed rate | D8: 0
A10: BOQ Ref | B10: Description | C10: Unit | D10: Qty | E10: Rate (£) | F10: Total (£) | G10: Notes / Qualifications
A11: P1 | B11: Plumbing preliminaries - RAMS, site set-up, travel/parking (Paisley town centre), consumables | C11: item | D11: 1 | E11: =INDEX('Build-up'!$H:$H,MATCH(A11,'Build-up'!$A:$A,0)) | F11: =D11*E11
A12: 2.12 | B12: Disconnect, remove & dispose of existing toilet, sink and plumbing pipework/fittings in WC's | C12: item | D12: 1 | E12: =INDEX('Build-up'!$H:$H,MATCH(A12,'Build-up'!$A:$A,0)) | F12: =D12*E12
A13: 2.13 | B13: Terminate and cap building services as required (plumbing services only) | C13: item | D13: 1 | E13: =INDEX('Build-up'!$H:$H,MATCH(A13,'Build-up'!$A:$A,0)) | F13: =D13*E13 | G13: Electrical by others
A14: 14.01 | B14: WC adjacent to kitchen - supply & install sanitaryware (soft-close WC, standalone basin) | C14: Budget | D14: 1 | E14: =INDEX('Build-up'!$H:$H,MATCH(A14,'Build-up'!$A:$A,0)) | F14: =D14*E14 | G14: Standard commercial range (Twyford/Armitage Shanks or equal)
A15: 14.03 | B15: Soap dispenser attached to wall | C15: item | D15: 1 | E15: =INDEX('Build-up'!$H:$H,MATCH(A15,'Build-up'!$A:$A,0)) | F15: =D15*E15
A16: 14.05 | B16: WC adjacent to rear staircase - supply & install sanitaryware (soft-close WC, standalone basin) | C16: Budget | D16: 1 | E16: =INDEX('Build-up'!$H:$H,MATCH(A16,'Build-up'!$A:$A,0)) | F16: =D16*E16 | G16: Standard commercial range
A17: 14.07 | B17: Soap dispenser attached to wall | C17: item | D17: 1 | E17: =INDEX('Build-up'!$H:$H,MATCH(A17,'Build-up'!$A:$A,0)) | F17: =D17*E17
A18: 14.10 | B18: Accessible WC (cafe) - Doc M service pack, supply & install | C18: item | D18: 1 | E18: =INDEX('Build-up'!$H:$H,MATCH(A18,'Build-up'!$A:$A,0)) | F18: =D18*E18 | G18: Doc M pack incl. rails, basin, lever tap
A19: 14.11 | B19: Accessible WC - wall-hung pan: concealed frame & cistern (extra over Doc M pack) | C19: Budget | D19: 1 | E19: =INDEX('Build-up'!$H:$H,MATCH(A19,'Build-up'!$A:$A,0)) | F19: =D19*E19 | G19: Omit if close-coupled Doc M pan acceptable
A20: 14.14 | B20: Soap dispenser attached to wall | C20: item | D20: 1 | E20: =INDEX('Build-up'!$H:$H,MATCH(A20,'Build-up'!$A:$A,0)) | F20: =D20*E20
A21: 15.01 | B21: Drainage above ground - accessible WC (WC & basin) incl. NEW 110mm SVP, AAV & access | C21: item | D21: 1 | E21: =INDEX('Build-up'!$H:$H,MATCH(A21,'Build-up'!$A:$A,0)) | F21: =D21*E21
A22: 15.02 | B22: Drainage above ground - WC facilities (WC & basin) into existing SVP | C22: item | D22: 1 | E22: =INDEX('Build-up'!$H:$H,MATCH(A22,'Build-up'!$A:$A,0)) | F22: =D22*E22 | G22: Assumes existing SVP sound; connection to cast iron via transition coupling
A23: 15.03 | B23: Drainage above ground - kitchen (sink, WHB, dishwasher) into existing SVP | C23: P.Sum | D23: 1 | E23: =INDEX('Build-up'!$H:$H,MATCH(A23,'Build-up'!$A:$A,0)) | F23: =D23*E23 | G23: Grease trap supply EXCLUDED - connections only allowed
A24: 15.04 | B24: Testing & commissioning of H&C water installations incl. chlorination & certificate | C24: item | D24: 1 | E24: =INDEX('Build-up'!$H:$H,MATCH(A24,'Build-up'!$A:$A,0)) | F24: =D24*E24 | G24: Chlorination to BS EN 806 / L8 with lab sample
A25: 16.03 | B25: Hot & cold water installation - accessible WC | C25: item | D25: 1 | E25: =INDEX('Build-up'!$H:$H,MATCH(A25,'Build-up'!$A:$A,0)) | F25: =D25*E25 | G25: Incl. TMV3, isolation, insulation
A26: 16.04 | B26: Hot & cold water installation - WC (rear stair) | C26: item | D26: 1 | E26: =INDEX('Build-up'!$H:$H,MATCH(A26,'Build-up'!$A:$A,0)) | F26: =D26*E26 | G26: Incl. TMV3, isolation, insulation
A27: 16.05 | B27: Hot & cold water installation - WC (adj. kitchen) | C27: item | D27: 1 | E27: =INDEX('Build-up'!$H:$H,MATCH(A27,'Build-up'!$A:$A,0)) | F27: =D27*E27 | G27: Incl. TMV3, isolation, insulation
A28: 16.06 | B28: Hot & cold water installation - kitchen facility (sink, WHB, dishwasher points) | C28: item | D28: 1 | E28: =INDEX('Build-up'!$H:$H,MATCH(A28,'Build-up'!$A:$A,0)) | F28: =D28*E28 | G28: WH04 excluded per BOQ
A29: 16.14 | B29: Water heater WH01 - HYCO IN30T 3kW, supply & install incl. expansion controls per detail | C29: item | D29: 1 | E29: =INDEX('Build-up'!$H:$H,MATCH(A29,'Build-up'!$A:$A,0)) | F29: =D29*E29 | G29: Electrical supply/isolator by electrician (BOQ 17.04)
A30: 18.42 | B30: Water heater WH02 - HYCO IN30T 3kW (BOQ numbering error - should read 16.15) | C30: item | D30: 1 | E30: =INDEX('Build-up'!$H:$H,MATCH(A30,'Build-up'!$A:$A,0)) | F30: =D30*E30
A31: 16.15 | B31: Water heater WH03 - HYCO IN30T 3kW, supply & install incl. expansion controls per detail | C31: item | D31: 1 | E31: =INDEX('Build-up'!$H:$H,MATCH(A31,'Build-up'!$A:$A,0)) | F31: =D31*E31
A32: 16.17 | B32: Testing & commissioning of mechanical (plumbing) services | C32: item | D32: 1 | E32: =INDEX('Build-up'!$H:$H,MATCH(A32,'Build-up'!$A:$A,0)) | F32: =D32*E32 | G32: Pressure test & commissioning heaters/TMVs
E34: TENDER TOTAL | F34: =SUM(F11:F32)
E35: Total labour hours | F35: =SUM('Build-up'!C:C)

Sheet Build-up
A1: Price build-up per BOQ item
A3: BOQ Ref | B3: Description | C3: Labour hours | D3: Labour (£) | E3: Materials net (£) | F3: Materials inc. mark-up (£) | G3: Labour inc. O&P (£) | H3: Item price (£)
A4: P1 | B4: Plumbing preliminaries - RAMS, site set-up, travel/parking (Paisley town centre), consumables | C4: 4 | D4: =C4*Tender!$D$6 | E4: =SUMIF(Materials!$A:$A,A4,Materials!$G:$G) | F4: =E4*(1+Tender!$D$7) | G4: =D4*(1+Tender!$D$8) | H4: =ROUND(F4+G4,0)
A5: 2.12 | B5: Disconnect, remove & dispose of existing toilet, sink and plumbing pipework/fittings in WC's | C5: 8 | D5: =C5*Tender!$D$6 | E5: =SUMIF(Materials!$A:$A,A5,Materials!$G:$G) | F5: =E5*(1+Tender!$D$7) | G5: =D5*(1+Tender!$D$8) | H5: =ROUND(F5+G5,0)
A6: 2.13 | B6: Terminate and cap building services as required (plumbing services only) | C6: 4 | D6: =C6*Tender!$D$6 | E6: =SUMIF(Materials!$A:$A,A6,Materials!$G:$G) | F6: =E6*(1+Tender!$D$7) | G6: =D6*(1+Tender!$D$8) | H6: =ROUND(F6+G6,0)
A7: 14.01 | B7: WC adjacent to kitchen - supply & install sanitaryware (soft-close WC, standalone basin) | C7: 6 | D7: =C7*Tender!$D$6 | E7: =SUMIF(Materials!$A:$A,A7,Materials!$G:$G) | F7: =E7*(1+Tender!$D$7) | G7: =D7*(1+Tender!$D$8) | H7: =ROUND(F7+G7,0)
A8: 14.03 | B8: Soap dispenser attached to wall | C8: 0.8 | D8: =C8*Tender!$D$6 | E8: =SUMIF(Materials!$A:$A,A8,Materials!$G:$G) | F8: =E8*(1+Tender!$D$7) | G8: =D8*(1+Tender!$D$8) | H8: =ROUND(F8+G8,0)
A9: 14.05 | B9: WC adjacent to rear staircase - supply & install sanitaryware (soft-close WC, standalone basin) | C9: 6 | D9: =C9*Tender!$D$6 | E9: =SUMIF(Materials!$A:$A,A9,Materials!$G:$G) | F9: =E9*(1+Tender!$D$7) | G9: =D9*(1+Tender!$D$8) | H9: =ROUND(F9+G9,0)
A10: 14.07 | B10: Soap dispenser attached to wall | C10: 0.8 | D10: =C10*Tender!$D$6 | E10: =SUMIF(Materials!$A:$A,A10,Materials!$G:$G) | F10: =E10*(1+Tender!$D$7) | G10: =D10*(1+Tender!$D$8) | H10: =ROUND(F10+G10,0)
A11: 14.10 | B11: Accessible WC (cafe) - Doc M service pack, supply & install | C11: 10 | D11: =C11*Tender!$D$6 | E11: =SUMIF(Materials!$A:$A,A11,Materials!$G:$G) | F11: =E11*(1+Tender!$D$7) | G11: =D11*(1+Tender!$D$8) | H11: =ROUND(F11+G11,0)
A12: 14.11 | B12: Accessible WC - wall-hung pan: concealed frame & cistern (extra over Doc M pack) | C12: 4 | D12: =C12*Tender!$D$6 | E12: =SUMIF(Materials!$A:$A,A12,Materials!$G:$G) | F12: =E12*(1+Tender!$D$7) | G12: =D12*(1+Tender!$D$8) | H12: =ROUND(F12+G12,0)
A13: 14.14 | B13: Soap dispenser attached to wall | C13: 0.8 | D13: =C13*Tender!$D$6 | E13: =SUMIF(Materials!$A:$A,A13,Materials!$G:$G) | F13: =E13*(1+Tender!$D$7) | G13: =D13*(1+Tender!$D$8) | H13: =ROUND(F13+G13,0)
A14: 15.01 | B14: Drainage above ground - accessible WC (WC & basin) incl. NEW 110mm SVP, AAV & access | C14: 16 | D14: =C14*Tender!$D$6 | E14: =SUMIF(Materials!$A:$A,A14,Materials!$G:$G) | F14: =E14*(1+Tender!$D$7) | G14: =D14*(1+Tender!$D$8) | H14: =ROUND(F14+G14,0)
A15: 15.02 | B15: Drainage above ground - WC facilities (WC & basin) into existing SVP | C15: 8 | D15: =C15*Tender!$D$6 | E15: =SUMIF(Materials!$A:$A,A15,Materials!$G:$G) | F15: =E15*(1+Tender!$D$7) | G15: =D15*(1+Tender!$D$8) | H15: =ROUND(F15+G15,0)
... A25: 16.17 | B25: Testing & commissioning of mechanical (plumbing) services | C25: 4 | D25: =C25*Tender!$D$6 | E25: =SUMIF(Materials!$A:$A,A25,Materials!$G:$G) | F25: =E25*(1+Tender!$D$7) | G25: =D25*(1+Tender!$D$8) | H25: =ROUND(F25+G25,0)
B26: TOTALS | C26: =SUM(C4:C25) | D26: =SUM(D4:D25) | E26: =SUM(E4:E25) | F26: =SUM(F4:F25) | G26: =SUM(G4:G25) | H26: =SUM(H4:H25)

Sheet Materials
A1: Materials take-off (from drawings E23025 (52) 001 BW3 & (53) 001 BW2) - rates are ESTIMATED trade prices, check with merchant
A3: BOQ Ref | B3: Section | C3: Item | D3: Qty | E3: Unit | F3: Rate (£) | G3: Total (£)
A4: P1 | B4: Hot & cold water | C4: Consumables - solder, flux, PTFE, solvent cement, fixings | D4: 1 | E4: lot | F4: 150 | G4: =D4*F4
A5: P1 | B5: General | C5: Parking / travel allowance | D5: 1 | E5: item | F5: 100 | G5: =D5*F5
A6: 2.12 | B6: Drainage | C6: 110mm soil blanking caps | D6: 2 | E6: no | F6: 6 | G6: =D6*F6
A7: 2.12 | B7: Drainage | C7: Waste disposal / skip share - old sanitaryware | D7: 1 | E7: item | F7: 150 | G7: =D7*F7
A8: 2.13 | B8: Hot & cold water | C8: Stop ends 15/22mm | D8: 8 | E8: no | F8: 3 | G8: =D8*F8
A9: 14.01 | B9: Drainage | C9: 32mm bottle trap | D9: 1 | E9: no | F9: 8 | G9: =D9*F9
A10: 14.01 | B10: Sanitaryware | C10: Close-coupled WC pan, cistern & soft-close seat (commercial) | D10: 1 | E10: no | F10: 180 | G10: =D10*F10
A11: 14.01 | B11: Sanitaryware | C11: Silicone, pan & basin fixings | D11: 1 | E11: lot | F11: 15 | G11: =D11*F11
A12: 14.01 | B12: Drainage | C12: WC pan connector 110mm | D12: 1 | E12: no | F12: 10 | G12: =D12*F12
A13: 14.01 | B13: Sanitaryware | C13: Wash hand basin, tap & fixings | D13: 1 | E13: no | F13: 150 | G13: =D13*F13
A14: 14.03 | B14: Sanitaryware | C14: Wall-mounted soap dispenser | D14: 1 | E14: no | F14: 25 | G14: =D14*F14
A15: 14.05 | B15: Drainage | C15: 32mm bottle trap | D15: 1 | E15: no | F15: 8 | G15: =D15*F15
... A165: 16.17 | B165: General | C165: Test gauge / commissioning consumables | D165: 1 | E165: lot | F165: 20 | G165: =D165*F165
F167: TOTAL | G167: =SUM(G4:G165)

Sheet Qualifications
A1: Tender qualifications, exclusions & programme
A3: Tender basis
A4: BOQ - Ground Floor Fit Out - Light House rev3; Tender Clarifications No.1 & No.2.
A5: Drawings: Kilbryde E23025 (52) 001 BW3 (above ground drainage), E23025 (53) 001 BW2 (hot & cold water); Framed Estates 697 AB 111C (GF plan), 697 AB 400A (accessible WC).
A6: Prices exclude VAT - domestic reverse charge applies. Subject to CIS. Tender valid for 30 days.
A7: Contract: Minor Works Building Contract for use in Scotland. Payment by monthly valuation.
A9: Items excluded / by others
A10: BOQ ref | B10: Item | C10: Comment
A11: 14.02 / 14.06 / 14.13 | B11: Hand dryers | C11: Supply by PC sum; install & wiring by electrician
A12: 14.04 / 14.08 / 14.12 | B12: Mirrors & colostomy shelves | C12: By joiner - can supply & fix on request
A13: 16.01 | B13: Door transfer grilles | C13: By joiner / ventilation - can price on request
A14: 16.08 - 16.11 | B14: Extract fans DEF01/DEF02 & ductwork | C14: By ventilation / electrician - can price on request
A15: 16.12 / 16.16 | B15: Kitchen extract KEP01 & water heater WH04 | C15: Excluded in BOQ
A16: 17.x | B16: All electrical works incl. isolators & spurs to water heaters | C16: By electrician
A17: 18.1 | B17: Builders work in connection (holes, boxing-in, access panels, lifting/relaying floors, making good) | C17: By main contractor
A18: GT01 | B18: Grease trap supply (Big Dipper W-250-ISE) - shown on drawing, not in BOQ | C18: Connections allowed in 15.03; supply can be priced on request
A20: Assumptions & clarifications
A21: 1. Existing SVP is sound and suitable for new connections; transition couplings allowed for connection to cast iron. Replacement of existing stack excluded.
A22: 2. Two incoming 22mm mains are marked 'TBC' on drawing (53) 001 - allowed for connection within 3m of fitting positions. Alterations to incoming supply/meter excluded.
A23: 3. Below-floor drainage assumes access via the suspended timber floor; lifting and relaying of flooring by main contractor/joiner.
A24: 4. Sanitaryware priced as standard commercial range (Twyford / Armitage Shanks or equal). Client-selected ranges to be adjusted.
A25: 5. Item 14.11: BOQ calls for a wall-hung pan in the accessible WC. A concealed frame is priced separately so it can be omitted if a close-coupled Doc M pan is accepted.
A26: 6. Water heaters: expansion controls (PRV, check valve, expansion vessel, relief valve) priced per the typical detail on drawing (53) 001. These are not normally required on instantaneous IN30T heaters - saving available if omitted.
A27: 7. Fire collars allowed where drainage passes through fire-rated construction (drawing note 8). General fire stopping by others (BOQ 13.06).
A28: 8. Items 15.04 and 16.17 (testing & commissioning) appear twice in the BOQ - priced once each without duplication: 15.04 = chlorination & certificate, 16.17 = pressure testing & commissioning.
A29: 9. Kitchen scope is TBC in the BOQ - 15.03 and 16.06 allow first fix & connections to sink, WHB and dishwasher positions shown on the drawings. Kitchen equipment, grease trap supply and WH04 excluded.
A30: 10. Works carried out during normal working hours (Mon-Fri, 8am-5pm) with clear access.
A32: Programme
... A35: Suggested overall contract duration for the fit-out: 8-10 weeks.
